{
  "name": "gc_500_9",
  "final_colors": 143,
  "final_time": 2303.43,
  "trace": [
    {
      "colors": 160,
      "time": 0.0821289,
      "elapsed": 0.0821289,
      "raw": "{\"colors\": 160, \"time\": 0.0821289}",
      "captured_at": 1783834675.049184
    },
    {
      "colors": 159,
      "time": 0.606666,
      "elapsed": 0.606666,
      "raw": "{\"colors\": 159, \"time\": 0.606666}",
      "captured_at": 1783834675.5737212
    },
    {
      "colors": 158,
      "time": 0.65199,
      "elapsed": 0.65199,
      "raw": "{\"colors\": 158, \"time\": 0.65199}",
      "captured_at": 1783834675.619045
    },
    {
      "colors": 157,
      "time": 0.722002,
      "elapsed": 0.722002,
      "raw": "{\"colors\": 157, \"time\": 0.722002}",
      "captured_at": 1783834675.689057
    },
    {
      "colors": 156,
      "time": 0.800296,
      "elapsed": 0.800296,
      "raw": "{\"colors\": 156, \"time\": 0.800296}",
      "captured_at": 1783834675.7673512
    },
    {
      "colors": 155,
      "time": 0.862884,
      "elapsed": 0.862884,
      "raw": "{\"colors\": 155, \"time\": 0.862884}",
      "captured_at": 1783834675.8299391
    },
    {
      "colors": 154,
      "time": 0.94762,
      "elapsed": 0.94762,
      "raw": "{\"colors\": 154, \"time\": 0.94762}",
      "captured_at": 1783834675.914675
    },
    {
      "colors": 153,
      "time": 1.00334,
      "elapsed": 1.00334,
      "raw": "{\"colors\": 153, \"time\": 1.00334}",
      "captured_at": 1783834675.970395
    },
    {
      "colors": 152,
      "time": 1.09613,
      "elapsed": 1.09613,
      "raw": "{\"colors\": 152, \"time\": 1.09613}",
      "captured_at": 1783834676.063185
    },
    {
      "colors": 151,
      "time": 1.21376,
      "elapsed": 1.21376,
      "raw": "{\"colors\": 151, \"time\": 1.21376}",
      "captured_at": 1783834676.180815
    },
    {
      "colors": 150,
      "time": 1.65663,
      "elapsed": 1.65663,
      "raw": "{\"colors\": 150, \"time\": 1.65663}",
      "captured_at": 1783834676.6236851
    },
    {
      "colors": 149,
      "time": 2.41884,
      "elapsed": 2.41884,
      "raw": "{\"colors\": 149, \"time\": 2.41884}",
      "captured_at": 1783834677.385895
    },
    {
      "colors": 148,
      "time": 2.68701,
      "elapsed": 2.68701,
      "raw": "{\"colors\": 148, \"time\": 2.68701}",
      "captured_at": 1783834677.6540651
    },
    {
      "colors": 147,
      "time": 3.61495,
      "elapsed": 3.61495,
      "raw": "{\"colors\": 147, \"time\": 3.61495}",
      "captured_at": 1783834678.582005
    },
    {
      "colors": 146,
      "time": 3.92994,
      "elapsed": 3.92994,
      "raw": "{\"colors\": 146, \"time\": 3.92994}",
      "captured_at": 1783834678.896995
    },
    {
      "colors": 145,
      "time": 6.42921,
      "elapsed": 6.42921,
      "raw": "{\"colors\": 145, \"time\": 6.42921}",
      "captured_at": 1783834681.396265
    },
    {
      "colors": 144,
      "time": 191.706,
      "elapsed": 191.706,
      "raw": "{\"colors\": 144, \"time\": 191.706}",
      "captured_at": 1783834866.6730552
    },
    {
      "colors": 143,
      "time": 2303.43,
      "elapsed": 2303.43,
      "raw": "{\"colors\": 143, \"time\": 2303.43}",
      "captured_at": 1783836978.3970551
    }
  ],
  "stdout": "",
  "stderr": [
    "{\"colors\": 160, \"time\": 0.0821289}\n",
    "{\"colors\": 159, \"time\": 0.606666}\n",
    "{\"colors\": 158, \"time\": 0.65199}\n",
    "{\"colors\": 157, \"time\": 0.722002}\n",
    "{\"colors\": 156, \"time\": 0.800296}\n",
    "{\"colors\": 155, \"time\": 0.862884}\n",
    "{\"colors\": 154, \"time\": 0.94762}\n",
    "{\"colors\": 153, \"time\": 1.00334}\n",
    "{\"colors\": 152, \"time\": 1.09613}\n",
    "{\"colors\": 151, \"time\": 1.21376}\n",
    "{\"colors\": 150, \"time\": 1.65663}\n",
    "{\"colors\": 149, \"time\": 2.41884}\n",
    "{\"colors\": 148, \"time\": 2.68701}\n",
    "{\"colors\": 147, \"time\": 3.61495}\n",
    "{\"colors\": 146, \"time\": 3.92994}\n",
    "{\"colors\": 145, \"time\": 6.42921}\n",
    "{\"colors\": 144, \"time\": 191.706}\n",
    "{\"colors\": 143, \"time\": 2303.43}\n"
  ],
  "exit_code": -9,
  "timed_out": true,
  "par2": 6000.0
}