{
  "name": "gc_500_9",
  "final_colors": 143,
  "final_time": 2372.22,
  "trace": [
    {
      "colors": 160,
      "time": 0.0573066,
      "elapsed": 0.0573066,
      "raw": "{\"colors\": 160, \"time\": 0.0573066}",
      "captured_at": 1783794957.8348827
    },
    {
      "colors": 159,
      "time": 0.566427,
      "elapsed": 0.566427,
      "raw": "{\"colors\": 159, \"time\": 0.566427}",
      "captured_at": 1783794958.3440032
    },
    {
      "colors": 158,
      "time": 0.61221,
      "elapsed": 0.61221,
      "raw": "{\"colors\": 158, \"time\": 0.61221}",
      "captured_at": 1783794958.3897862
    },
    {
      "colors": 157,
      "time": 0.683026,
      "elapsed": 0.683026,
      "raw": "{\"colors\": 157, \"time\": 0.683026}",
      "captured_at": 1783794958.4606023
    },
    {
      "colors": 156,
      "time": 0.761188,
      "elapsed": 0.761188,
      "raw": "{\"colors\": 156, \"time\": 0.761188}",
      "captured_at": 1783794958.5387642
    },
    {
      "colors": 155,
      "time": 0.823868,
      "elapsed": 0.823868,
      "raw": "{\"colors\": 155, \"time\": 0.823868}",
      "captured_at": 1783794958.6014442
    },
    {
      "colors": 154,
      "time": 0.90761,
      "elapsed": 0.90761,
      "raw": "{\"colors\": 154, \"time\": 0.90761}",
      "captured_at": 1783794958.6851861
    },
    {
      "colors": 153,
      "time": 0.963132,
      "elapsed": 0.963132,
      "raw": "{\"colors\": 153, \"time\": 0.963132}",
      "captured_at": 1783794958.740708
    },
    {
      "colors": 152,
      "time": 1.05542,
      "elapsed": 1.05542,
      "raw": "{\"colors\": 152, \"time\": 1.05542}",
      "captured_at": 1783794958.8329961
    },
    {
      "colors": 151,
      "time": 1.17282,
      "elapsed": 1.17282,
      "raw": "{\"colors\": 151, \"time\": 1.17282}",
      "captured_at": 1783794958.9503963
    },
    {
      "colors": 150,
      "time": 1.61687,
      "elapsed": 1.61687,
      "raw": "{\"colors\": 150, \"time\": 1.61687}",
      "captured_at": 1783794959.3944461
    },
    {
      "colors": 149,
      "time": 2.37689,
      "elapsed": 2.37689,
      "raw": "{\"colors\": 149, \"time\": 2.37689}",
      "captured_at": 1783794960.1544662
    },
    {
      "colors": 148,
      "time": 2.64472,
      "elapsed": 2.64472,
      "raw": "{\"colors\": 148, \"time\": 2.64472}",
      "captured_at": 1783794960.4222963
    },
    {
      "colors": 147,
      "time": 3.57323,
      "elapsed": 3.57323,
      "raw": "{\"colors\": 147, \"time\": 3.57323}",
      "captured_at": 1783794961.3508062
    },
    {
      "colors": 146,
      "time": 3.88799,
      "elapsed": 3.88799,
      "raw": "{\"colors\": 146, \"time\": 3.88799}",
      "captured_at": 1783794961.6655662
    },
    {
      "colors": 145,
      "time": 5.98291,
      "elapsed": 5.98291,
      "raw": "{\"colors\": 145, \"time\": 5.98291}",
      "captured_at": 1783794963.7604861
    },
    {
      "colors": 144,
      "time": 173.816,
      "elapsed": 173.816,
      "raw": "{\"colors\": 144, \"time\": 173.816}",
      "captured_at": 1783795131.5935762
    },
    {
      "colors": 143,
      "time": 2372.22,
      "elapsed": 2372.22,
      "raw": "{\"colors\": 143, \"time\": 2372.22}",
      "captured_at": 1783797329.9975762
    }
  ],
  "stdout": "",
  "stderr": [
    "{\"colors\": 160, \"time\": 0.0573066}\n",
    "{\"colors\": 159, \"time\": 0.566427}\n",
    "{\"colors\": 158, \"time\": 0.61221}\n",
    "{\"colors\": 157, \"time\": 0.683026}\n",
    "{\"colors\": 156, \"time\": 0.761188}\n",
    "{\"colors\": 155, \"time\": 0.823868}\n",
    "{\"colors\": 154, \"time\": 0.90761}\n",
    "{\"colors\": 153, \"time\": 0.963132}\n",
    "{\"colors\": 152, \"time\": 1.05542}\n",
    "{\"colors\": 151, \"time\": 1.17282}\n",
    "{\"colors\": 150, \"time\": 1.61687}\n",
    "{\"colors\": 149, \"time\": 2.37689}\n",
    "{\"colors\": 148, \"time\": 2.64472}\n",
    "{\"colors\": 147, \"time\": 3.57323}\n",
    "{\"colors\": 146, \"time\": 3.88799}\n",
    "{\"colors\": 145, \"time\": 5.98291}\n",
    "{\"colors\": 144, \"time\": 173.816}\n",
    "{\"colors\": 143, \"time\": 2372.22}\n"
  ],
  "exit_code": -9,
  "timed_out": true,
  "par2": 6000.0
}